rooster/__init__.py
rooster/__main__.py
rooster/_cache.py
rooster/_changelog.py
rooster/_cli.py
rooster/_config.py
rooster/_git.py
rooster/_github.py
rooster/_http.py
rooster/_pyproject.py
rooster/_testing.py
rooster/_versions.py
rooster-0.1.0.dist-info/WHEEL
rooster-0.1.0.dist-info/entry_points.txt
rooster-0.1.0.dist-info/METADATA
rooster-0.1.0.dist-info/RECORD
